{
    "instaloader": {
        "node_type": "Post",
        "version": "4.2.8"
    },
    "node": {
        "__typename": "GraphSidecar",
        "caption_is_edited": false,
        "commenting_disabled_for_viewer": false,
        "comments_disabled": false,
        "dimensions": {
            "height": 1080,
            "width": 1080
        },
        "display_resources": [
            {
                "config_height": 640,
                "config_width": 640,
                "src": "https://scontent-arn2-2.cdninstagram.com/v/t51.2885-15/sh0.08/e35/s640x640/37323439_834108613445729_7329296819437961216_n.jpg?_nc_ht=scontent-arn2-2.cdninstagram.com&_nc_cat=105&_nc_ohc=u-cGqE4jcXgAX_PbEbr&oh=ca2158b5bf482d6df555096f7c7241d7&oe=5F0D2848"
            },
            {
                "config_height": 750,
                "config_width": 750,
                "src": "https://scontent-arn2-2.cdninstagram.com/v/t51.2885-15/sh0.08/e35/s750x750/37323439_834108613445729_7329296819437961216_n.jpg?_nc_ht=scontent-arn2-2.cdninstagram.com&_nc_cat=105&_nc_ohc=u-cGqE4jcXgAX_PbEbr&oh=4d5e680ca8cbab2a04fe736a3c616b4b&oe=5F0EF5C8"
            },
            {
                "config_height": 1080,
                "config_width": 1080,
                "src": "https://scontent-arn2-2.cdninstagram.com/v/t51.2885-15/e35/37323439_834108613445729_7329296819437961216_n.jpg?_nc_ht=scontent-arn2-2.cdninstagram.com&_nc_cat=105&_nc_ohc=u-cGqE4jcXgAX_PbEbr&oh=59553576cf63d9b56465c9e8b9afc6a5&oe=5F0E5823"
            }
        ],
        "display_url": "https://scontent-arn2-2.cdninstagram.com/v/t51.2885-15/e35/37323439_834108613445729_7329296819437961216_n.jpg?_nc_ht=scontent-arn2-2.cdninstagram.com&_nc_cat=105&_nc_ohc=u-cGqE4jcXgAX_PbEbr&oh=59553576cf63d9b56465c9e8b9afc6a5&oe=5F0E5823",
        "edge_media_preview_comment": {
            "count": 2,
            "edges": [
                {
                    "node": {
                        "created_at": 1532323648,
                        "did_report_as_spam": false,
                        "edge_liked_by": {
                            "count": 0
                        },
                        "id": "17938131187138017",
                        "is_restricted_pending": false,
                        "owner": {
                            "id": "1386775151",
                            "is_verified": false,
                            "profile_pic_url": "https://scontent-arn2-2.cdninstagram.com/v/t51.2885-19/s150x150/81042856_442499243307718_8726702400997425152_n.jpg?_nc_ht=scontent-arn2-2.cdninstagram.com&_nc_ohc=O6Q6qaAbpqsAX-umBsq&oh=6de6492e281cf82f584d04a0d1a4429a&oe=5F0D3091",
                            "username": "zubkova_julia_"
                        },
                        "text": "\u0421\u043f\u0430\u0441\u0438\u0431\u043e \u0410\u043d\u044e\u0442\ud83d\ude18",
                        "viewer_has_liked": false
                    }
                },
                {
                    "node": {
                        "created_at": 1532339716,
                        "did_report_as_spam": false,
                        "edge_liked_by": {
                            "count": 0
                        },
                        "id": "17864378590265445",
                        "is_restricted_pending": false,
                        "owner": {
                            "id": "6018741911",
                            "is_verified": false,
                            "profile_pic_url": "https://scontent-arn2-2.cdninstagram.com/v/t51.2885-19/s150x150/46755187_209716489919678_824716386067546112_n.jpg?_nc_ht=scontent-arn2-2.cdninstagram.com&_nc_ohc=wQ14QivV0SkAX-06KjT&oh=86828f7cecb4ae8985bdc678bf6e0b8a&oe=5F0D934B",
                            "username": "anna.sutiagina"
                        },
                        "text": "@zubkova_julia_\u041f\u043e\u0436\u0430\u043b\u0443\u0439\u0441\u0442\u0430, \u043d\u0430\u0434\u0435\u044e\u0441\u044c \u043f\u043e\u043d\u0440\u0430\u0432\u0438\u0442\u0441\u044f",
                        "viewer_has_liked": false
                    }
                }
            ]
        },
        "edge_media_preview_like": {
            "count": 26,
            "edges": []
        },
        "edge_media_to_caption": {
            "edges": [
                {
                    "node": {
                        "text": "\u0421\u043b\u0430\u0434\u043e\u0441\u0442\u0438 \u0434\u043b\u044f \u0434\u0435\u0442\u0441\u043a\u043e\u0433\u043e \u043f\u0440\u0430\u0437\u0434\u043d\u0438\u043a\u0430!#\u0441\u043b\u0430\u0434\u043e\u0441\u0442\u0438 #\u0441\u043b\u0430\u0434\u043a\u0438\u0439\u0441\u0442\u043e\u043b #\u0441\u043b\u0430\u0434\u043a\u0430\u044f\u0436\u0438\u0437\u043d\u044c #\u0441\u043b\u0430\u0434\u043e\u0441\u0442\u044c\u0440\u0430\u0434\u043e\u0441\u0442\u044c"
                    }
                }
            ]
        },
        "edge_media_to_comment": {
            "count": 2
        },
        "edge_media_to_hoisted_comment": {
            "edges": []
        },
        "edge_media_to_parent_comment": {
            "count": 2,
            "edges": [
                {
                    "node": {
                        "created_at": 1532323648,
                        "did_report_as_spam": false,
                        "edge_liked_by": {
                            "count": 0
                        },
                        "edge_threaded_comments": {
                            "count": 1,
                            "edges": [
                                {
                                    "node": {
                                        "created_at": 1532339716,
                                        "did_report_as_spam": false,
                                        "edge_liked_by": {
                                            "count": 0
                                        },
                                        "id": "17864378590265445",
                                        "is_restricted_pending": false,
                                        "owner": {
                                            "id": "6018741911",
                                            "is_verified": false,
                                            "profile_pic_url": "https://scontent-arn2-2.cdninstagram.com/v/t51.2885-19/s150x150/46755187_209716489919678_824716386067546112_n.jpg?_nc_ht=scontent-arn2-2.cdninstagram.com&_nc_ohc=wQ14QivV0SkAX-06KjT&oh=86828f7cecb4ae8985bdc678bf6e0b8a&oe=5F0D934B",
                                            "username": "anna.sutiagina"
                                        },
                                        "text": "@zubkova_julia_\u041f\u043e\u0436\u0430\u043b\u0443\u0439\u0441\u0442\u0430, \u043d\u0430\u0434\u0435\u044e\u0441\u044c \u043f\u043e\u043d\u0440\u0430\u0432\u0438\u0442\u0441\u044f",
                                        "viewer_has_liked": false
                                    }
                                }
                            ],
                            "page_info": {
                                "end_cursor": null,
                                "has_next_page": false
                            }
                        },
                        "id": "17938131187138017",
                        "is_restricted_pending": false,
                        "owner": {
                            "id": "1386775151",
                            "is_verified": false,
                            "profile_pic_url": "https://scontent-arn2-2.cdninstagram.com/v/t51.2885-19/s150x150/81042856_442499243307718_8726702400997425152_n.jpg?_nc_ht=scontent-arn2-2.cdninstagram.com&_nc_ohc=O6Q6qaAbpqsAX-umBsq&oh=6de6492e281cf82f584d04a0d1a4429a&oe=5F0D3091",
                            "username": "zubkova_julia_"
                        },
                        "text": "\u0421\u043f\u0430\u0441\u0438\u0431\u043e \u0410\u043d\u044e\u0442\ud83d\ude18",
                        "viewer_has_liked": false
                    }
                }
            ],
            "page_info": {
                "end_cursor": null,
                "has_next_page": false
            }
        },
        "edge_media_to_sponsor_user": {
            "edges": []
        },
        "edge_media_to_tagged_user": {
            "edges": []
        },
        "edge_related_profiles": {
            "edges": []
        },
        "edge_sidecar_to_children": {
            "edges": [
                {
                    "node": {
                        "__typename": "GraphImage",
                        "accessibility_caption": "Photo by \u0410\u043d\u043d\u0430 \u0421\u0443\u0442\u044f\u0433\u0438\u043d\u0430 on July 22, 2018.",
                        "dimensions": {
                            "height": 1080,
                            "width": 1080
                        },
                        "display_resources": [
                            {
                                "config_height": 640,
                                "config_width": 640,
                                "src": "https://scontent-arn2-2.cdninstagram.com/v/t51.2885-15/sh0.08/e35/s640x640/37323439_834108613445729_7329296819437961216_n.jpg?_nc_ht=scontent-arn2-2.cdninstagram.com&_nc_cat=105&_nc_ohc=u-cGqE4jcXgAX_PbEbr&oh=ca2158b5bf482d6df555096f7c7241d7&oe=5F0D2848"
                            },
                            {
                                "config_height": 750,
                                "config_width": 750,
                                "src": "https://scontent-arn2-2.cdninstagram.com/v/t51.2885-15/sh0.08/e35/s750x750/37323439_834108613445729_7329296819437961216_n.jpg?_nc_ht=scontent-arn2-2.cdninstagram.com&_nc_cat=105&_nc_ohc=u-cGqE4jcXgAX_PbEbr&oh=4d5e680ca8cbab2a04fe736a3c616b4b&oe=5F0EF5C8"
                            },
                            {
                                "config_height": 1080,
                                "config_width": 1080,
                                "src": "https://scontent-arn2-2.cdninstagram.com/v/t51.2885-15/e35/37323439_834108613445729_7329296819437961216_n.jpg?_nc_ht=scontent-arn2-2.cdninstagram.com&_nc_cat=105&_nc_ohc=u-cGqE4jcXgAX_PbEbr&oh=59553576cf63d9b56465c9e8b9afc6a5&oe=5F0E5823"
                            }
                        ],
                        "display_url": "https://scontent-arn2-2.cdninstagram.com/v/t51.2885-15/e35/37323439_834108613445729_7329296819437961216_n.jpg?_nc_ht=scontent-arn2-2.cdninstagram.com&_nc_cat=105&_nc_ohc=u-cGqE4jcXgAX_PbEbr&oh=59553576cf63d9b56465c9e8b9afc6a5&oe=5F0E5823",
                        "edge_media_to_tagged_user": {
                            "edges": []
                        },
                        "fact_check_information": null,
                        "fact_check_overall_rating": null,
                        "gating_info": null,
                        "id": "1829335792772639251",
                        "is_video": false,
                        "media_overlay_info": null,
                        "media_preview": "ACoqhpKuiLGMDJPrjj+lSCNNvmMOPQcVmXzK9jNxQVIGSMCtBXL5C/KOuc9vfNSBFHB5+o4P+f8AIqrC5n0RkEd6nxWiFUjaxx7f/W6CmiGE9wPbmk1YFK/T9Sus2DwMmnNKw5ODu/h9h+n4VH5UjdTn86ikiKAbicdBgep9zSt/X9bBa/X0/rqWo7gEkABc/wA/x/lUmApzyAOST39hVdYEccsPbkdfXjvTN0a5DsSOmCD/APrp38yeV2sl+n9fIlRgOfXnNKdxOQDipUjXhk4Xrheh/D1p5jH979WrNu5rYhSfY+1umewOfzOP5VKUbcSu3n+8CePT0rR2jaTjtVROlUxRKphZWBKrIPRQAPxFPm3SD95Hhfr29cgE8e1WqUVJdyksdsoyp6cgEkc037Q390f99f8A1q0yoZTuAP15qhgUMaP/2Q==",
                        "sensitivity_friction_info": null,
                        "shortcode": "BljGzYXHuoT",
                        "tracking_token": "eyJ2ZXJzaW9uIjo1LCJwYXlsb2FkIjp7ImlzX2FuYWx5dGljc190cmFja2VkIjp0cnVlLCJ1dWlkIjoiNGZlYjVjM2U5NjUyNDlkMGI5MjhkZTYxYjJlY2NlYTMxODI5MzM1NzkyNzcyNjM5MjUxIn0sInNpZ25hdHVyZSI6IiJ9"
                    }
                },
                {
                    "node": {
                        "__typename": "GraphImage",
                        "accessibility_caption": "Photo by \u0410\u043d\u043d\u0430 \u0421\u0443\u0442\u044f\u0433\u0438\u043d\u0430 on July 22, 2018.",
                        "dimensions": {
                            "height": 1080,
                            "width": 1080
                        },
                        "display_resources": [
                            {
                                "config_height": 640,
                                "config_width": 640,
                                "src": "https://scontent-arn2-1.cdninstagram.com/v/t51.2885-15/sh0.08/e35/s640x640/37259862_1542362472536913_5106853274724597760_n.jpg?_nc_ht=scontent-arn2-1.cdninstagram.com&_nc_cat=109&_nc_ohc=yZ-kbZIoGPYAX-7InzP&oh=1d6d771bd3f0fce56b98639d6c27132d&oe=5F0FBCAD"
                            },
                            {
                                "config_height": 750,
                                "config_width": 750,
                                "src": "https://scontent-arn2-1.cdninstagram.com/v/t51.2885-15/sh0.08/e35/s750x750/37259862_1542362472536913_5106853274724597760_n.jpg?_nc_ht=scontent-arn2-1.cdninstagram.com&_nc_cat=109&_nc_ohc=yZ-kbZIoGPYAX-7InzP&oh=b62ef141a784d34f8c2eb144892e137f&oe=5F0E73E9"
                            },
                            {
                                "config_height": 1080,
                                "config_width": 1080,
                                "src": "https://scontent-arn2-1.cdninstagram.com/v/t51.2885-15/e35/37259862_1542362472536913_5106853274724597760_n.jpg?_nc_ht=scontent-arn2-1.cdninstagram.com&_nc_cat=109&_nc_ohc=yZ-kbZIoGPYAX-7InzP&oh=acecf9b8f03c75e4e6b35e9c0e59bba4&oe=5F0CE817"
                            }
                        ],
                        "display_url": "https://scontent-arn2-1.cdninstagram.com/v/t51.2885-15/e35/37259862_1542362472536913_5106853274724597760_n.jpg?_nc_ht=scontent-arn2-1.cdninstagram.com&_nc_cat=109&_nc_ohc=yZ-kbZIoGPYAX-7InzP&oh=acecf9b8f03c75e4e6b35e9c0e59bba4&oe=5F0CE817",
                        "edge_media_to_tagged_user": {
                            "edges": []
                        },
                        "fact_check_information": null,
                        "fact_check_overall_rating": null,
                        "gating_info": null,
                        "id": "1829335802754948155",
                        "is_video": false,
                        "media_overlay_info": null,
                        "media_preview": "ACoqhpcZo+0ugPtjhucevT+fPHPtT2l8wHGAQuRjj689f1qLF3I9pPAGTTjA44IIqurHHy8jpg9j7mkEsnOW56fn2+lFguS+WynkYp+KgSZ0xg5PXnk/nUxlk/2fxxn+VFguOeEY2odz9PY9e3rjjrz6UQxyRclSR33DAz9B/wDqqWKIMN2Aeckj/HqMVYRXG5VPJHU9weg9u9S2VZdCpIolPy4j75/hJ+n9aiEapknbISDwOg9D79MYFPe2kY84wvp0+gqJ433DaMgY7+nX3HOapCaS66vy/wCCTLaGVQ6t1HIIzyP8KplFBwWye59amUuihl43E/L1/P8AlS74O6nPsaBJX/pG2YGjyUPAXAUf3j0P4daY88cYCyH5h97Gff8AnVK1Yh8A8cfzrTMatIMgHg9QP71R5lW11K80oQDCttxnIHGOv50yWRchW+TcAeeuD2wOhqbUSREcccgVn2/zod3zYIxnnH0p3swtzIuKgIyOh/8A1UeXT7cAJ+J/nU1UjN6M/9k=",
                        "sensitivity_friction_info": null,
                        "shortcode": "BljGzhqHNw7",
                        "tracking_token": "eyJ2ZXJzaW9uIjo1LCJwYXlsb2FkIjp7ImlzX2FuYWx5dGljc190cmFja2VkIjp0cnVlLCJ1dWlkIjoiNGZlYjVjM2U5NjUyNDlkMGI5MjhkZTYxYjJlY2NlYTMxODI5MzM1ODAyNzU0OTQ4MTU1In0sInNpZ25hdHVyZSI6IiJ9"
                    }
                },
                {
                    "node": {
                        "__typename": "GraphImage",
                        "accessibility_caption": "Photo by \u0410\u043d\u043d\u0430 \u0421\u0443\u0442\u044f\u0433\u0438\u043d\u0430 on July 22, 2018.",
                        "dimensions": {
                            "height": 1080,
                            "width": 1080
                        },
                        "display_resources": [
                            {
                                "config_height": 640,
                                "config_width": 640,
                                "src": "https://scontent-arn2-1.cdninstagram.com/v/t51.2885-15/sh0.08/e35/s640x640/37329457_1795153327235467_2401113707485593600_n.jpg?_nc_ht=scontent-arn2-1.cdninstagram.com&_nc_cat=107&_nc_ohc=cdSyK74mO6QAX8tmBcI&oh=5d09d1c1db53047ceb4081b0eb14056a&oe=5F0CA2CA"
                            },
                            {
                                "config_height": 750,
                                "config_width": 750,
                                "src": "https://scontent-arn2-1.cdninstagram.com/v/t51.2885-15/sh0.08/e35/s750x750/37329457_1795153327235467_2401113707485593600_n.jpg?_nc_ht=scontent-arn2-1.cdninstagram.com&_nc_cat=107&_nc_ohc=cdSyK74mO6QAX8tmBcI&oh=c6292d9e770525491c89cdebee3ad08b&oe=5F0DEC8E"
                            },
                            {
                                "config_height": 1080,
                                "config_width": 1080,
                                "src": "https://scontent-arn2-1.cdninstagram.com/v/t51.2885-15/e35/37329457_1795153327235467_2401113707485593600_n.jpg?_nc_ht=scontent-arn2-1.cdninstagram.com&_nc_cat=107&_nc_ohc=cdSyK74mO6QAX8tmBcI&oh=4c66024934c43eb3351b524a5483f180&oe=5F106574"
                            }
                        ],
                        "display_url": "https://scontent-arn2-1.cdninstagram.com/v/t51.2885-15/e35/37329457_1795153327235467_2401113707485593600_n.jpg?_nc_ht=scontent-arn2-1.cdninstagram.com&_nc_cat=107&_nc_ohc=cdSyK74mO6QAX8tmBcI&oh=4c66024934c43eb3351b524a5483f180&oe=5F106574",
                        "edge_media_to_tagged_user": {
                            "edges": []
                        },
                        "fact_check_information": null,
                        "fact_check_overall_rating": null,
                        "gating_info": null,
                        "id": "1829335811244387288",
                        "is_video": false,
                        "media_overlay_info": null,
                        "media_preview": "ACoqVZ+CCpHTtUkEin8faqyyOCCpBAx19T1GeM0+4YoMjndzken+elYNtaG1uhYeUR8YyW/T3P4VWScHhhjJwCOQaqB2PUnA4575/wA/nUkT9fUHp7f4+/8A9erW2pUlyxvuy8eRgdaAB7UyHnrnHXJ9fT8KkLjPU/lWLk76akLUo4ZumeepHrWi1t5iAZ+YYx2yR2/H9Ka7GQHaCADgkYGfUc0hMsYDYbceMBdxAPOSPX9K6OXroQ5WaWzT/rXrfYqG1fHIP07VOloFwTyx646D6evue/NOkEroHOWCn7oByT7gc89vrVy4hLbcHByPvHnHoP8AP40JJb6m0pX929u9lf8AX+vMjEeAQOcfrUHlsfT8qvKrLlW2k8/d4wvHB/2uuaXyV9D+Z/xrPkXS6RmnbcZGYwAD0xwB/n/9dDXJY9OmOf6/X/CoW6iol+8PxrTYi1731uWDdE/c4z1HHUen5CqzyEFjnuTye/8AhgdKB978RTJuh/3j/SkXaxYW88vHyg7gOnH+fU0n2qPvuz3qpJ94/QfyplCEf//Z",
                        "sensitivity_friction_info": null,
                        "shortcode": "BljGzpkH2vY",
                        "tracking_token": "eyJ2ZXJzaW9uIjo1LCJwYXlsb2FkIjp7ImlzX2FuYWx5dGljc190cmFja2VkIjp0cnVlLCJ1dWlkIjoiNGZlYjVjM2U5NjUyNDlkMGI5MjhkZTYxYjJlY2NlYTMxODI5MzM1ODExMjQ0Mzg3Mjg4In0sInNpZ25hdHVyZSI6IiJ9"
                    }
                },
                {
                    "node": {
                        "__typename": "GraphImage",
                        "accessibility_caption": "Photo by \u0410\u043d\u043d\u0430 \u0421\u0443\u0442\u044f\u0433\u0438\u043d\u0430 on July 22, 2018.",
                        "dimensions": {
                            "height": 1080,
                            "width": 1080
                        },
                        "display_resources": [
                            {
                                "config_height": 640,
                                "config_width": 640,
                                "src": "https://scontent-arn2-2.cdninstagram.com/v/t51.2885-15/sh0.08/e35/s640x640/37380812_1383749611756841_3249916334573617152_n.jpg?_nc_ht=scontent-arn2-2.cdninstagram.com&_nc_cat=105&_nc_ohc=prY3idFiR2kAX9jFYxC&oh=25ccb44082e67f8c50fee194195e9144&oe=5F0DCE61"
                            },
                            {
                                "config_height": 750,
                                "config_width": 750,
                                "src": "https://scontent-arn2-2.cdninstagram.com/v/t51.2885-15/sh0.08/e35/s750x750/37380812_1383749611756841_3249916334573617152_n.jpg?_nc_ht=scontent-arn2-2.cdninstagram.com&_nc_cat=105&_nc_ohc=prY3idFiR2kAX9jFYxC&oh=0bea3a066344a3a8bc9b233646f246d9&oe=5F0F3C25"
                            },
                            {
                                "config_height": 1080,
                                "config_width": 1080,
                                "src": "https://scontent-arn2-2.cdninstagram.com/v/t51.2885-15/e35/37380812_1383749611756841_3249916334573617152_n.jpg?_nc_ht=scontent-arn2-2.cdninstagram.com&_nc_cat=105&_nc_ohc=prY3idFiR2kAX9jFYxC&oh=5320a6ba7438cd87eb2367a5e8fc602d&oe=5F0E9BDB"
                            }
                        ],
                        "display_url": "https://scontent-arn2-2.cdninstagram.com/v/t51.2885-15/e35/37380812_1383749611756841_3249916334573617152_n.jpg?_nc_ht=scontent-arn2-2.cdninstagram.com&_nc_cat=105&_nc_ohc=prY3idFiR2kAX9jFYxC&oh=5320a6ba7438cd87eb2367a5e8fc602d&oe=5F0E9BDB",
                        "edge_media_to_tagged_user": {
                            "edges": []
                        },
                        "fact_check_information": null,
                        "fact_check_overall_rating": null,
                        "gating_info": null,
                        "id": "1829335820496879552",
                        "is_video": false,
                        "media_overlay_info": null,
                        "media_preview": "ACoqnwaXaaiZixDDgEAj0x+HXPWpY5xtI+8Vxk+mf61D0KWt9ACml20zdtYM3RiOO2DjFLO6joe/QdscU0728yHKyba2/Ek2buD3qiQBwSfyq9EQyA9eSM9+PWlMYJ//AFVQ0+oxpFbp279AAP5AU6B02kgAbiAT68cf/WqFnEhOVAzz+P8A9erCxxpHtUZ3nJzycjj+nFZWtdMaSfvrr/X6EL5LZJwAR7/hUj5YlkwGzg+p9P0qNbdHIDjAznjj6Z/HrUspXJfGOoOOv+HPf/Gh7JImPVt/8AaoIVs9iD/Q1NVeDadwHVxg/gDj2/KpFfIBrRabjTvqtSNrWUcqAT25/wA/0qwkMkcajh2A5xxySTwe/pVmih67gko6JWKBhnZhwFGck5zjHbH+fU1NLC4JKcgnOM4/nVmiiwWVrdClBFKJcsoVAD3BJPbGPT3pjLtJGOnFaFYUsjh25PU9z60xJJaLRH//2Q==",
                        "sensitivity_friction_info": null,
                        "shortcode": "BljGzyLnT_A",
                        "tracking_token": "eyJ2ZXJzaW9uIjo1LCJwYXlsb2FkIjp7ImlzX2FuYWx5dGljc190cmFja2VkIjp0cnVlLCJ1dWlkIjoiNGZlYjVjM2U5NjUyNDlkMGI5MjhkZTYxYjJlY2NlYTMxODI5MzM1ODIwNDk2ODc5NTUyIn0sInNpZ25hdHVyZSI6IiJ9"
                    }
                }
            ]
        },
        "edge_web_media_to_related_media": {
            "edges": []
        },
        "fact_check_information": null,
        "fact_check_overall_rating": null,
        "gating_info": null,
        "has_ranked_comments": false,
        "id": "1829337637786601214",
        "is_ad": false,
        "is_video": false,
        "location": {
            "address_json": "{\"street_address\": \"\", \"zip_code\": \"\", \"city_name\": \"Oryekhovo, Moskovskaya Oblast', Russia\", \"region_name\": \"\", \"country_code\": \"RU\", \"exact_city_match\": true, \"exact_region_match\": false, \"exact_country_match\": false}",
            "has_public_page": true,
            "id": "642101644",
            "name": "Oryekhovo, Moskovskaya Oblast', Russia",
            "slug": "oryekhovo-moskovskaya-oblast-russia"
        },
        "media_overlay_info": null,
        "media_preview": null,
        "owner": {
            "biography": "\u0412\u043a\u0443\u0441\u043d\u043e\u0441\u0442\u0438 \u0432 \u041e\u0440\u0435\u0445\u043e\u0432\u043e-\u0417\u0443\u0435\u0432\u043e\n\ud83c\udf82\u0422\u043e\u0440\u0442\u044b \n\u043e\u0442 1100 \u0440\u0443\u0431/\u043a\u0433\n\ud83c\udf82\u041a\u0430\u043f\u043a\u0435\u0439\u043a\u0438\n \u043e\u0442 130 \u0440\u0443\u0431/\u0448\u0442\n\ud83c\udf82\u0422\u0440\u0430\u0439\u0444\u043b\u044b \n  200 \u0440\u0443\u0431/\u0448\u0442\n\ud83c\udf61\ud83c\udf62 \u041a\u0435\u043d\u0434\u0438 \u0431\u0430\u0440\nViber, WhatsApp, Direct \n\ud83d\udcf289262201610",
            "blocked_by_viewer": false,
            "business_category_name": "Creators & Celebrities",
            "category_enum": "PERSONAL_BLOG",
            "category_id": "2700",
            "connected_fb_page": null,
            "country_block": false,
            "edge_felix_video_timeline": {
                "count": 0,
                "edges": [],
                "page_info": {
                    "end_cursor": null,
                    "has_next_page": false
                }
            },
            "edge_follow": {
                "count": 276
            },
            "edge_followed_by": {
                "count": 819
            },
            "edge_mutual_followed_by": {
                "count": 0,
                "edges": []
            },
            "edge_related_profiles": {
                "edges": []
            },
            "external_url": null,
            "external_url_linkshimmed": null,
            "followed_by_viewer": false,
            "follows_viewer": false,
            "full_name": "\u0410\u043d\u043d\u0430 \u0421\u0443\u0442\u044f\u0433\u0438\u043d\u0430",
            "has_ar_effects": false,
            "has_blocked_viewer": false,
            "has_channel": false,
            "has_requested_viewer": false,
            "highlight_reel_count": 12,
            "id": "6018741911",
            "is_business_account": true,
            "is_joined_recently": false,
            "is_private": false,
            "is_verified": false,
            "overall_category_name": null,
            "profile_pic_url": "https://scontent-arn2-2.cdninstagram.com/v/t51.2885-19/s150x150/46755187_209716489919678_824716386067546112_n.jpg?_nc_ht=scontent-arn2-2.cdninstagram.com&_nc_ohc=wQ14QivV0SkAX-06KjT&oh=86828f7cecb4ae8985bdc678bf6e0b8a&oe=5F0D934B",
            "profile_pic_url_hd": "https://scontent-arn2-2.cdninstagram.com/v/t51.2885-19/s320x320/46755187_209716489919678_824716386067546112_n.jpg?_nc_ht=scontent-arn2-2.cdninstagram.com&_nc_ohc=wQ14QivV0SkAX-06KjT&oh=0d8a7895ee835bf68d4e21cbecc270e7&oe=5F0F2CC8",
            "requested_by_viewer": false,
            "restricted_by_viewer": null,
            "username": "anna.sutiagina"
        },
        "sensitivity_friction_info": null,
        "shortcode": "BljHOOqhcb-",
        "taken_at_timestamp": 1532294061,
        "thumbnail_resources": [
            {
                "config_height": 150,
                "config_width": 150,
                "src": "https://scontent-arn2-2.cdninstagram.com/v/t51.2885-15/e35/s150x150/37323439_834108613445729_7329296819437961216_n.jpg?_nc_ht=scontent-arn2-2.cdninstagram.com&_nc_cat=105&_nc_ohc=u-cGqE4jcXgAX_PbEbr&oh=6a3f24b68eaea993c1d05550f975575a&oe=5F0ECAE1"
            },
            {
                "config_height": 240,
                "config_width": 240,
                "src": "https://scontent-arn2-2.cdninstagram.com/v/t51.2885-15/e35/s240x240/37323439_834108613445729_7329296819437961216_n.jpg?_nc_ht=scontent-arn2-2.cdninstagram.com&_nc_cat=105&_nc_ohc=u-cGqE4jcXgAX_PbEbr&oh=f635cdbb386f568a8d97cdd46beef900&oe=5F1001AB"
            },
            {
                "config_height": 320,
                "config_width": 320,
                "src": "https://scontent-arn2-2.cdninstagram.com/v/t51.2885-15/e35/s320x320/37323439_834108613445729_7329296819437961216_n.jpg?_nc_ht=scontent-arn2-2.cdninstagram.com&_nc_cat=105&_nc_ohc=u-cGqE4jcXgAX_PbEbr&oh=d4d4ed54e089b7ff659a98dd5e3c3baf&oe=5F0DAB11"
            },
            {
                "config_height": 480,
                "config_width": 480,
                "src": "https://scontent-arn2-2.cdninstagram.com/v/t51.2885-15/e35/s480x480/37323439_834108613445729_7329296819437961216_n.jpg?_nc_ht=scontent-arn2-2.cdninstagram.com&_nc_cat=105&_nc_ohc=u-cGqE4jcXgAX_PbEbr&oh=fa78723a00a72b23acd36fc44ec2d50f&oe=5F0E534B"
            },
            {
                "config_height": 640,
                "config_width": 640,
                "src": "https://scontent-arn2-2.cdninstagram.com/v/t51.2885-15/sh0.08/e35/s640x640/37323439_834108613445729_7329296819437961216_n.jpg?_nc_ht=scontent-arn2-2.cdninstagram.com&_nc_cat=105&_nc_ohc=u-cGqE4jcXgAX_PbEbr&oh=ca2158b5bf482d6df555096f7c7241d7&oe=5F0D2848"
            }
        ],
        "thumbnail_src": "https://scontent-arn2-2.cdninstagram.com/v/t51.2885-15/sh0.08/e35/s640x640/37323439_834108613445729_7329296819437961216_n.jpg?_nc_ht=scontent-arn2-2.cdninstagram.com&_nc_cat=105&_nc_ohc=u-cGqE4jcXgAX_PbEbr&oh=ca2158b5bf482d6df555096f7c7241d7&oe=5F0D2848",
        "tracking_token": "eyJ2ZXJzaW9uIjo1LCJwYXlsb2FkIjp7ImlzX2FuYWx5dGljc190cmFja2VkIjp0cnVlLCJ1dWlkIjoiNGZlYjVjM2U5NjUyNDlkMGI5MjhkZTYxYjJlY2NlYTMxODI5MzM3NjM3Nzg2NjAxMjE0In0sInNpZ25hdHVyZSI6IiJ9",
        "viewer_can_reshare": true,
        "viewer_has_liked": false,
        "viewer_has_saved": false,
        "viewer_has_saved_to_collection": false,
        "viewer_in_photo_of_you": false
    }
}